{"Response":"Success","Type":100,"Aggregated":false,"Data":[{"time":1517011200,"close":1.8,"high":10,"low":1,"open":1,"volumefrom":121.01,"volumeto":194.04},{"time":1517097600,"close":2.7,"high":20,"low":0.63,"open":1.8,"volumefrom":557.63,"volumeto":2233.14},{"time":1517184000,"close":5.26,"high":12,"low":2.71,"open":2.71,"volumefrom":150.45,"volumeto":918.24},{"time":1517270400,"close":0.2405,"high":6,"low":0.14,"open":5.26,"volumefrom":3893.33,"volumeto":1169.55},{"time":1517356800,"close":0.1279,"high":0.2405,"low":0.07212,"open":0.2405,"volumefrom":2412.25,"volumeto":407.18},{"time":1517443200,"close":0.126,"high":1,"low":0.08,"open":0.1279,"volumefrom":2948.9,"volumeto":497.09},{"time":1517529600,"close":0.085,"high":0.3,"low":0.085,"open":0.126,"volumefrom":767.68,"volumeto":91.22},{"time":1517616000,"close":0.0811,"high":0.085,"low":0.0811,"open":0.085,"volumefrom":60.65,"volumeto":4.92},{"time":1517702400,"close":0.15,"high":0.2799,"low":0.0811,"open":0.0811,"volumefrom":103.61,"volumeto":15.87},{"time":1517788800,"close":0.081,"high":0.135,"low":0.081,"open":0.09,"volumefrom":3643.05,"volumeto":408.57},{"time":1517875200,"close":0.08,"high":0.2,"low":0.08,"open":0.081,"volumefrom":1576.38,"volumeto":228.75},{"time":1517961600,"close":0.07212,"high":0.12,"low":0.07212,"open":0.08,"volumefrom":886.3,"volumeto":66.63},{"time":1518048000,"close":0.07212,"high":0.07212,"low":0.07212,"open":0.07212,"volumefrom":18.66,"volumeto":1.35},{"time":1518134400,"close":0.07212,"high":0.07212,"low":0.07212,"open":0.07212,"volumefrom":0,"volumeto":0},{"time":1518220800,"close":0.072,"high":0.118,"low":0.072,"open":0.07212,"volumefrom":4.19,"volumeto":0.38},{"time":1518307200,"close":0.072,"high":0.072,"low":0.072,"open":0.072,"volumefrom":0,"volumeto":0},{"time":1518393600,"close":0.1199,"high":0.1199,"low":0.072,"open":0.072,"volumefrom":1187.48,"volumeto":130.4},{"time":1518480000,"close":0.09,"high":0.1199,"low":0.08797,"open":0.1199,"volumefrom":34.86,"volumeto":3.07},{"time":1518566400,"close":0.072,"high":0.1039,"low":0.072,"open":0.09,"volumefrom":1482.28,"volumeto":133.42},{"time":1518652800,"close":0.1039,"high":0.1039,"low":0.072,"open":0.072,"volumefrom":50.36,"volumeto":5.23},{"time":1518739200,"close":0.1039,"high":0.1039,"low":0.1039,"open":0.1039,"volumefrom":13.47,"volumeto":1.4},{"time":1518825600,"close":0.1,"high":0.45,"low":0.1,"open":0.1039,"volumefrom":1331.69,"volumeto":175.05},{"time":1518912000,"close":0.07206,"high":0.39,"low":0.072,"open":0.072,"volumefrom":178.17,"volumeto":17.34},{"time":1518998400,"close":0.1521,"high":0.39,"low":0.07206,"open":0.07206,"volumefrom":192.82,"volumeto":68.54},{"time":1519084800,"close":0.0966,"high":0.1521,"low":0.09,"open":0.1521,"volumefrom":667.84,"volumeto":60.47},{"time":1519171200,"close":0.09,"high":0.1098,"low":0.09,"open":0.0966,"volumefrom":1348.07,"volumeto":145.35},{"time":1519257600,"close":0.075,"high":0.09,"low":0.075,"open":0.09,"volumefrom":1.58,"volumeto":0.1183},{"time":1519344000,"close":0.075,"high":0.075,"low":0.075,"open":0.075,"volumefrom":0,"volumeto":0},{"time":1519430400,"close":0.075,"high":0.075,"low":0.075,"open":0.075,"volumefrom":0,"volumeto":0},{"time":1519516800,"close":0.075,"high":0.075,"low":0.075,"open":0.075,"volumefrom":0,"volumeto":0},{"time":1519603200,"close":0.1031,"high":0.1031,"low":0.075,"open":0.075,"volumefrom":84.83,"volumeto":7.68},{"time":1519689600,"close":0.1031,"high":0.1031,"low":0.1031,"open":0.1031,"volumefrom":0,"volumeto":0},{"time":1519776000,"close":0.08,"high":0.1031,"low":0.075,"open":0.1031,"volumefrom":8.12,"volumeto":0.624},{"time":1519862400,"close":0.085,"high":0.085,"low":0.08,"open":0.08,"volumefrom":3,"volumeto":0.255}],"TimeTo":1519862400,"TimeFrom":1517011200000,"FirstValueInArray":true,"ConversionType":{"type":"direct","conversionSymbol":""}}