{"Response":"Success","Type":100,"Aggregated":false,"Data":[{"time":1513814400,"high":3.74,"low":3.74,"open":3.74,"volumefrom":0.06648,"volumeto":0.2486,"close":3.74},{"time":1513900800,"high":3.12,"low":2.3,"open":3.12,"volumefrom":389.53,"volumeto":895.92,"close":2.3},{"time":1513987200,"high":3.43,"low":2.45,"open":2.45,"volumefrom":19.46,"volumeto":66.75,"close":3.43},{"time":1514073600,"high":3.31,"low":1.35,"open":3.31,"volumefrom":1735.01,"volumeto":4927.43,"close":2.84},{"time":1514160000,"high":3.25,"low":2.39,"open":3.04,"volumefrom":174.35,"volumeto":416.7,"close":2.39},{"time":1514246400,"high":2.49,"low":2.49,"open":2.49,"volumefrom":42.14,"volumeto":104.93,"close":2.49},{"time":1514332800,"high":2.96,"low":2.22,"open":2.44,"volumefrom":746.9,"volumeto":2210.82,"close":2.96},{"time":1514419200,"high":2.87,"low":2.05,"open":2.87,"volumefrom":330.2,"volumeto":676.91,"close":2.05},{"time":1514505600,"high":2.86,"low":2.12,"open":2.12,"volumefrom":2762.17,"volumeto":5855.8,"close":2.12},{"time":1514592000,"high":2.55,"low":0.2148,"open":1.99,"volumefrom":2331.34,"volumeto":4849.19,"close":2.08},{"time":1514678400,"high":2.5,"low":0.2678,"open":2.22,"volumefrom":6548.27,"volumeto":14537.16,"close":2.22},{"time":1514764800,"high":2.5,"low":1.56,"open":2.27,"volumefrom":1569.91,"volumeto":3579.39,"close":2.28},{"time":1514851200,"high":2.67,"low":0.9327,"open":2.6,"volumefrom":1213.14,"volumeto":3239.08,"close":2.67},{"time":1514937600,"high":2.92,"low":2.73,"open":2.92,"volumefrom":105.62,"volumeto":303.13,"close":2.87},{"time":1515024000,"high":2.88,"low":1.89,"open":2.88,"volumefrom":631.3,"volumeto":1622.44,"close":2.57},{"time":1515110400,"high":2.64,"low":1.45,"open":2.64,"volumefrom":3884.11,"volumeto":10254.05,"close":2.64},{"time":1515196800,"high":4.93,"low":2.13,"open":2.74,"volumefrom":10488.28,"volumeto":31674.61,"close":3.02},{"time":1515283200,"high":3.35,"low":2.23,"open":3.35,"volumefrom":691.72,"volumeto":1549.45,"close":2.24},{"time":1515369600,"high":2.83,"low":1.25,"open":2.27,"volumefrom":2614.58,"volumeto":5961.24,"close":2.28},{"time":1515456000,"high":2.84,"low":2.18,"open":2.59,"volumefrom":1921.16,"volumeto":5148.71,"close":2.68},{"time":1515542400,"high":2.59,"low":1.66,"open":2.59,"volumefrom":5004.21,"volumeto":10608.93,"close":2.12},{"time":1515628800,"high":1.98,"low":1.52,"open":1.94,"volumefrom":4735.61,"volumeto":9139.73,"close":1.93},{"time":1515715200,"high":2.14,"low":2.06,"open":2.14,"volumefrom":1938.46,"volumeto":4012.61,"close":2.07},{"time":1515801600,"high":2.44,"low":1.98,"open":2.25,"volumefrom":5539.85,"volumeto":10968.9,"close":1.98},{"time":1515888000,"high":2.12,"low":1.94,"open":1.94,"volumefrom":5560.93,"volumeto":10955.03,"close":1.97},{"time":1515974400,"high":2.02,"low":1.76,"open":1.86,"volumefrom":3955.05,"volumeto":7989.2,"close":2.02},{"time":1516060800,"high":1.66,"low":1.05,"open":1.66,"volumefrom":3665.6,"volumeto":5278.46,"close":1.44},{"time":1516147200,"high":1.77,"low":1.41,"open":1.41,"volumefrom":612.22,"volumeto":1083.63,"close":1.77},{"time":1516233600,"high":1.72,"low":1.5,"open":1.5,"volumefrom":150.52,"volumeto":258.89,"close":1.72},{"time":1516320000,"high":1.76,"low":0.8507,"open":1.76,"volumefrom":5901.07,"volumeto":5020.04,"close":0.8507},{"time":1516406400,"high":1.76,"low":1.47,"open":1.47,"volumefrom":1572.3,"volumeto":2358.45,"close":1.5},{"time":1516492800,"high":1.69,"low":1.37,"open":1.54,"volumefrom":4895.62,"volumeto":7637.17,"close":1.56},{"time":1516579200,"high":1.49,"low":1.49,"open":1.49,"volumefrom":0,"volumeto":0,"close":1.49},{"time":1516665600,"high":1.52,"low":1.2,"open":1.52,"volumefrom":4076.95,"volumeto":5626.19,"close":1.38},{"time":1516752000,"high":1.69,"low":1.27,"open":1.49,"volumefrom":4912.88,"volumeto":8155.38,"close":1.66},{"time":1516838400,"high":1.75,"low":1.28,"open":1.64,"volumefrom":6239.08,"volumeto":9608.18,"close":1.54},{"time":1516924800,"high":1.81,"low":1.37,"open":1.54,"volumefrom":6554.98,"volumeto":8980.32,"close":1.37},{"time":1517011200,"high":1.8,"low":1.45,"open":1.45,"volumefrom":3626.26,"volumeto":5693.23,"close":1.57},{"time":1517097600,"high":1.79,"low":1.48,"open":1.74,"volumefrom":3492.07,"volumeto":6215.88,"close":1.78},{"time":1517184000,"high":1.66,"low":1.42,"open":1.54,"volumefrom":8662.28,"volumeto":13253.29,"close":1.53},{"time":1517270400,"high":1.54,"low":1.18,"open":1.39,"volumefrom":7195.45,"volumeto":9426.04,"close":1.31},{"time":1517356800,"high":1.58,"low":1.13,"open":1.37,"volumefrom":4245.78,"volumeto":5646.89,"close":1.33},{"time":1517443200,"high":1.42,"low":1.13,"open":1.23,"volumefrom":10583.95,"volumeto":12277.38,"close":1.16},{"time":1517529600,"high":1.22,"low":0.9432,"open":1.04,"volumefrom":10225.67,"volumeto":12373.06,"close":1.21},{"time":1517616000,"high":1.29,"low":1.07,"open":1.28,"volumefrom":18822.14,"volumeto":20139.69,"close":1.07},{"time":1517702400,"high":1.07,"low":0.9153,"open":0.9153,"volumefrom":3356.46,"volumeto":3111.1,"close":0.9269},{"time":1517788800,"high":1,"low":0.7785,"open":0.7785,"volumefrom":6445.91,"volumeto":6445.91,"close":1},{"time":1517875200,"high":1.22,"low":0.9216,"open":1.13,"volumefrom":20027.76,"volumeto":21029.15,"close":1.05},{"time":1517961600,"high":1.15,"low":1,"open":1,"volumefrom":2223.9,"volumeto":2246.14,"close":1.01},{"time":1518048000,"high":1.2,"low":1.09,"open":1.1,"volumefrom":2435.22,"volumeto":2654.39,"close":1.09},{"time":1518134400,"high":1.27,"low":1.1,"open":1.17,"volumefrom":3846.54,"volumeto":4231.19,"close":1.1},{"time":1518220800,"high":1.07,"low":1.06,"open":1.07,"volumefrom":711.74,"volumeto":754.44,"close":1.06},{"time":1518307200,"high":1.02,"low":1.01,"open":1.01,"volumefrom":2430.72,"volumeto":2479.33,"close":1.02},{"time":1518393600,"high":1.19,"low":1.08,"open":1.09,"volumefrom":8037.63,"volumeto":8680.64,"close":1.08},{"time":1518480000,"high":1.08,"low":0.9671,"open":1.05,"volumefrom":6262.02,"volumeto":6108.6,"close":0.9755},{"time":1518566400,"high":1.21,"low":1.06,"open":1.08,"volumefrom":648.78,"volumeto":746.1,"close":1.15},{"time":1518652800,"high":1.22,"low":1.09,"open":1.16,"volumefrom":2650.5,"volumeto":3233.61,"close":1.22},{"time":1518739200,"high":1.38,"low":1.14,"open":1.24,"volumefrom":3904.32,"volumeto":4880.4,"close":1.25},{"time":1518825600,"high":1.37,"low":1.22,"open":1.3,"volumefrom":1717.33,"volumeto":2352.74,"close":1.37},{"time":1518912000,"high":1.4,"low":1.14,"open":1.28,"volumefrom":2243,"volumeto":2669.17,"close":1.19},{"time":1518998400,"high":1.25,"low":1.11,"open":1.22,"volumefrom":7960.7,"volumeto":9871.27,"close":1.24},{"time":1519084800,"high":1.2,"low":1.03,"open":1.17,"volumefrom":6036.73,"volumeto":7244.08,"close":1.2},{"time":1519171200,"high":1.23,"low":1.04,"open":1.13,"volumefrom":886.01,"volumeto":921.45,"close":1.04},{"time":1519257600,"high":1.04,"low":0.9833,"open":1,"volumefrom":279.1,"volumeto":290.26,"close":1.04},{"time":1519344000,"high":1.1,"low":0.6838,"open":1.1,"volumefrom":500.32,"volumeto":342.12,"close":0.6838},{"time":1519430400,"high":1.01,"low":0.6668,"open":0.6668,"volumefrom":804.85,"volumeto":812.9,"close":1.01},{"time":1519516800,"high":1.02,"low":0.09268,"open":1.02,"volumefrom":299.03,"volumeto":292.48,"close":0.9781},{"time":1519603200,"high":1.01,"low":0.7809,"open":1.01,"volumefrom":649.87,"volumeto":507.48,"close":0.7809},{"time":1519689600,"high":1,"low":0.1917,"open":0.9919,"volumefrom":1650.84,"volumeto":1650.84,"close":1},{"time":1519776000,"high":0.9869,"low":0.7791,"open":0.9784,"volumefrom":2454.28,"volumeto":1915.07,"close":0.7803},{"time":1519862400,"high":0.9321,"low":0.7926,"open":0.7939,"volumefrom":7254,"volumeto":5779.26,"close":0.7926}],"TimeTo":1519862400,"TimeFrom":1513814400000,"FirstValueInArray":true,"ConversionType":{"type":"multiply","conversionSymbol":"ETH"}}