{"Response":"Success","Type":100,"Aggregated":false,"Data":[{"time":1515974400,"close":2.8,"high":3.6,"low":2.3,"open":2.8,"volumefrom":30869.16,"volumeto":94972.15},{"time":1516060800,"close":2.2,"high":3.3,"low":1.8,"open":2.8,"volumefrom":43425.59,"volumeto":103477.87},{"time":1516147200,"close":2.5,"high":2.5,"low":1.7,"open":2.1,"volumefrom":22217.87,"volumeto":43343.45},{"time":1516233600,"close":2.2,"high":2.5,"low":2,"open":2.5,"volumefrom":9129.53,"volumeto":21070.99},{"time":1516320000,"close":2.9,"high":2.9,"low":2.2,"open":2.2,"volumefrom":15049.74,"volumeto":37672.48},{"time":1516406400,"close":2.8,"high":2.9,"low":2.5,"open":2.9,"volumefrom":10572.79,"volumeto":29178.22},{"time":1516492800,"close":2.3,"high":2.8,"low":2,"open":2.8,"volumefrom":11030.55,"volumeto":25974.39},{"time":1516579200,"close":2.2,"high":2.3,"low":1.9,"open":2.3,"volumefrom":45846.08,"volumeto":98921.82},{"time":1516665600,"close":2.1,"high":2.4,"low":1.9,"open":2.2,"volumefrom":19898.37,"volumeto":42730.57},{"time":1516752000,"close":2,"high":2.3,"low":2,"open":2.1,"volumefrom":5496.17,"volumeto":11769.86},{"time":1516838400,"close":2.1,"high":2.3,"low":1.8,"open":2,"volumefrom":8691.23,"volumeto":18044.69},{"time":1516924800,"close":2,"high":2.2,"low":1.9,"open":2.1,"volumefrom":1162.69,"volumeto":2391.52},{"time":1517011200,"close":1.9,"high":2,"low":1.8,"open":2,"volumefrom":5023.67,"volumeto":9663.77},{"time":1517097600,"close":1.7,"high":2.1,"low":1.5,"open":1.9,"volumefrom":19290.68,"volumeto":30860},{"time":1517184000,"close":1.9,"high":2.1,"low":1.6,"open":1.7,"volumefrom":7789.45,"volumeto":13889.5},{"time":1517270400,"close":1.8,"high":2.2,"low":1.5,"open":1.9,"volumefrom":10139.63,"volumeto":19567.82},{"time":1517356800,"close":1.6,"high":1.8,"low":1.5,"open":1.8,"volumefrom":7380.77,"volumeto":11871.24},{"time":1517443200,"close":1.3,"high":1.8,"low":0.1,"open":1.6,"volumefrom":14028.64,"volumeto":19655.84},{"time":1517529600,"close":1.4,"high":1.6,"low":0.9,"open":1.3,"volumefrom":12692.13,"volumeto":15158.3},{"time":1517616000,"close":1.4,"high":1.6,"low":1.3,"open":1.4,"volumefrom":5105.81,"volumeto":7355.76},{"time":1517702400,"close":1.4,"high":1.6,"low":1.2,"open":1.4,"volumefrom":7420.21,"volumeto":10290.49},{"time":1517788800,"close":1.3,"high":1.5,"low":1.1,"open":1.4,"volumefrom":24784.21,"volumeto":30861.17},{"time":1517875200,"close":1.8,"high":1.8,"low":1,"open":1.3,"volumefrom":47345.33,"volumeto":54098.26},{"time":1517961600,"close":1.4,"high":1.9,"low":1.4,"open":1.8,"volumefrom":22941.94,"volumeto":39029.36},{"time":1518048000,"close":1.5,"high":1.7,"low":1.3,"open":1.4,"volumefrom":7726.46,"volumeto":11553.06},{"time":1518134400,"close":1.5,"high":1.7,"low":1.5,"open":1.5,"volumefrom":5814.93,"volumeto":9268.86},{"time":1518220800,"close":1.6,"high":2.1,"low":1.5,"open":1.5,"volumefrom":38712.13,"volumeto":70255.32},{"time":1518307200,"close":1.7,"high":1.8,"low":1.5,"open":1.6,"volumefrom":8624.18,"volumeto":14485.53},{"time":1518393600,"close":1.7,"high":1.9,"low":1.6,"open":1.7,"volumefrom":2300.48,"volumeto":4059.42},{"time":1518480000,"close":1.6,"high":1.8,"low":1.5,"open":1.7,"volumefrom":4477.05,"volumeto":7274.42},{"time":1518566400,"close":1.4,"high":1.7,"low":1.3,"open":1.6,"volumefrom":7519.26,"volumeto":11018.84},{"time":1518652800,"close":1.6,"high":1.7,"low":1.3,"open":1.4,"volumefrom":8008.01,"volumeto":12287.91},{"time":1518739200,"close":1.5,"high":1.7,"low":1.5,"open":1.6,"volumefrom":2364.48,"volumeto":3772.99},{"time":1518825600,"close":1.7,"high":1.7,"low":1.5,"open":1.5,"volumefrom":1390.68,"volumeto":2179.25},{"time":1518912000,"close":1.4,"high":1.7,"low":1.3,"open":1.7,"volumefrom":4689.73,"volumeto":6922.58},{"time":1518998400,"close":1.7,"high":1.7,"low":1.4,"open":1.4,"volumefrom":7647.01,"volumeto":12051.78},{"time":1519084800,"close":1.4,"high":1.7,"low":1.4,"open":1.7,"volumefrom":5228.36,"volumeto":8347.16},{"time":1519171200,"close":1.5,"high":1.5,"low":1.4,"open":1.4,"volumefrom":3653.35,"volumeto":5182.13},{"time":1519257600,"close":1.4,"high":1.6,"low":1.4,"open":1.5,"volumefrom":2344.67,"volumeto":3487.39},{"time":1519344000,"close":1.5,"high":1.6,"low":1.4,"open":1.4,"volumefrom":2621.35,"volumeto":3906.27},{"time":1519430400,"close":1.4,"high":1.6,"low":1.4,"open":1.5,"volumefrom":2473.46,"volumeto":3510.34},{"time":1519516800,"close":1.4,"high":1.6,"low":1.3,"open":1.4,"volumefrom":4333.63,"volumeto":6079.63},{"time":1519603200,"close":1.3,"high":1.5,"low":1.1,"open":1.4,"volumefrom":4922.03,"volumeto":6260.78},{"time":1519689600,"close":1.5,"high":1.6,"low":1.2,"open":1.3,"volumefrom":11922.1,"volumeto":16721.71},{"time":1519776000,"close":1.3,"high":1.6,"low":1.2,"open":1.5,"volumefrom":29475.33,"volumeto":38949.51},{"time":1519862400,"close":1.3,"high":1.4,"low":1.3,"open":1.3,"volumefrom":168.18,"volumeto":218.63}],"TimeTo":1519862400,"TimeFrom":1515974400000,"FirstValueInArray":true,"ConversionType":{"type":"direct","conversionSymbol":""}}