{"Response":"Success","Type":100,"Aggregated":false,"Data":[{"time":1497052800,"high":26.1,"low":0.377,"open":0.377,"volumefrom":227.63,"volumeto":1320.25,"close":5.8},{"time":1497139200,"high":11.89,"low":2.91,"open":5.95,"volumefrom":128.77,"volumeto":374.72,"close":2.91},{"time":1497225600,"high":6.38,"low":2.6,"open":2.6,"volumefrom":775.9,"volumeto":4950.24,"close":6.38},{"time":1497312000,"high":9.77,"low":2.71,"open":6.51,"volumefrom":68.47,"volumeto":297.16,"close":4.34},{"time":1497398400,"high":7.59,"low":3.95,"open":3.95,"volumefrom":216.42,"volumeto":1601.51,"close":7.4},{"time":1497484800,"high":7.32,"low":4.64,"open":7.32,"volumefrom":133.49,"volumeto":619.39,"close":4.64},{"time":1497571200,"high":7.27,"low":4.77,"open":4.77,"volumefrom":358.08,"volumeto":2513.72,"close":7.02},{"time":1497657600,"high":7.43,"low":4.17,"open":7.43,"volumefrom":52.78,"volumeto":273.4,"close":5.18},{"time":1497744000,"high":5.08,"low":2.82,"open":4.95,"volumefrom":258,"volumeto":1310.64,"close":5.08},{"time":1497830400,"high":5.23,"low":2.91,"open":5.23,"volumefrom":65,"volumeto":189.15,"close":2.91},{"time":1497916800,"high":4.96,"low":2.48,"open":3.06,"volumefrom":117.49,"volumeto":323.1,"close":2.75},{"time":1498003200,"high":2.68,"low":0.8836,"open":2.68,"volumefrom":241.53,"volumeto":647.3,"close":2.68},{"time":1498089600,"high":2.72,"low":1.63,"open":2.72,"volumefrom":281.57,"volumeto":458.96,"close":1.63},{"time":1498176000,"high":4.33,"low":1.63,"open":1.63,"volumefrom":641.23,"volumeto":2776.53,"close":4.33},{"time":1498262400,"high":4.14,"low":4.14,"open":4.14,"volumefrom":0,"volumeto":0,"close":4.14},{"time":1498348800,"high":4.06,"low":4.06,"open":4.06,"volumefrom":350.92,"volumeto":1424.74,"close":4.06},{"time":1498435200,"high":3.91,"low":1.47,"open":3.91,"volumefrom":449.83,"volumeto":1749.84,"close":3.89},{"time":1498521600,"high":4.11,"low":4.11,"open":4.11,"volumefrom":0,"volumeto":0,"close":4.11},{"time":1498608000,"high":4.1,"low":1.55,"open":4.1,"volumefrom":278.54,"volumeto":1142.01,"close":4.1},{"time":1498694400,"high":4.07,"low":1.54,"open":4.07,"volumefrom":828.85,"volumeto":2121.86,"close":2.56},{"time":1498780800,"high":2.48,"low":2.48,"open":2.48,"volumefrom":499.99,"volumeto":1239.98,"close":2.48},{"time":1498867200,"high":3.13,"low":1.45,"open":2.42,"volumefrom":812.05,"volumeto":2541.72,"close":3.13},{"time":1498953600,"high":3.27,"low":3.27,"open":3.27,"volumefrom":377.34,"volumeto":1233.9,"close":3.27},{"time":1499040000,"high":3.32,"low":1.6,"open":3.32,"volumefrom":162.33,"volumeto":538.94,"close":3.32},{"time":1499126400,"high":3.37,"low":1.58,"open":3.37,"volumefrom":430.32,"volumeto":1441.57,"close":3.35},{"time":1499212800,"high":3.36,"low":3.21,"open":3.36,"volumefrom":382.67,"volumeto":1228.37,"close":3.21},{"time":1499299200,"high":3.19,"low":3.14,"open":3.19,"volumefrom":510.31,"volumeto":1602.37,"close":3.14},{"time":1499385600,"high":3.02,"low":2.49,"open":3.02,"volumefrom":569.66,"volumeto":1418.45,"close":2.49},{"time":1499472000,"high":2.54,"low":1.54,"open":2.54,"volumefrom":351.1,"volumeto":631.98,"close":1.8},{"time":1499558400,"high":3.99,"low":1.76,"open":1.76,"volumefrom":4833.98,"volumeto":19287.58,"close":3.99},{"time":1499644800,"high":4.21,"low":1.53,"open":3.72,"volumefrom":408.38,"volumeto":1719.28,"close":4.21},{"time":1499731200,"high":4.17,"low":3.72,"open":4.17,"volumefrom":250.99,"volumeto":991.41,"close":3.95},{"time":1499817600,"high":8.65,"low":2.16,"open":4.08,"volumefrom":198.53,"volumeto":1717.28,"close":8.65},{"time":1499904000,"high":13.13,"low":8.5,"open":8.5,"volumefrom":332.86,"volumeto":4370.45,"close":13.13},{"time":1499990400,"high":12.41,"low":12.29,"open":12.41,"volumefrom":60.69,"volumeto":745.88,"close":12.29},{"time":1500076800,"high":10.86,"low":5.06,"open":10.86,"volumefrom":104.31,"volumeto":1132.81,"close":10.86},{"time":1500163200,"high":10.53,"low":10.53,"open":10.53,"volumefrom":44.94,"volumeto":473.22,"close":10.53},{"time":1500249600,"high":12.28,"low":12.24,"open":12.28,"volumefrom":100.41,"volumeto":1229.02,"close":12.24},{"time":1500336000,"high":12.71,"low":5.94,"open":12.71,"volumefrom":53.77,"volumeto":682.34,"close":12.69},{"time":1500422400,"high":12.49,"low":11.41,"open":12.49,"volumefrom":62.88,"volumeto":717.46,"close":11.41},{"time":1500508800,"high":14.33,"low":11.46,"open":14.33,"volumefrom":162.89,"volumeto":1866.72,"close":11.46},{"time":1500595200,"high":10.7,"low":2.55,"open":10.7,"volumefrom":64.89,"volumeto":694.32,"close":10.7},{"time":1500681600,"high":11.35,"low":11.34,"open":11.35,"volumefrom":49.47,"volumeto":560.99,"close":11.34},{"time":1500768000,"high":11.03,"low":11.02,"open":11.02,"volumefrom":41.47,"volumeto":457.41,"close":11.03},{"time":1500854400,"high":11.05,"low":11.05,"open":11.05,"volumefrom":43.47,"volumeto":480.34,"close":11.05},{"time":1500940800,"high":10.33,"low":10.33,"open":10.33,"volumefrom":40,"volumeto":413.2,"close":10.33},{"time":1501027200,"high":10.24,"low":10.24,"open":10.24,"volumefrom":85,"volumeto":870.4,"close":10.24},{"time":1501113600,"high":10.77,"low":10.77,"open":10.77,"volumefrom":76,"volumeto":818.52,"close":10.77},{"time":1501200000,"high":11.23,"low":11.23,"open":11.23,"volumefrom":0,"volumeto":0,"close":11.23},{"time":1501286400,"high":10.92,"low":9.43,"open":10.66,"volumefrom":60,"volumeto":565.8,"close":9.43},{"time":1501372800,"high":9.54,"low":5.53,"open":9.54,"volumefrom":119.17,"volumeto":1136.88,"close":9.54},{"time":1501459200,"high":9.95,"low":9.95,"open":9.95,"volumefrom":29.97,"volumeto":298.2,"close":9.95},{"time":1501545600,"high":9.48,"low":2.62,"open":9.48,"volumefrom":93.88,"volumeto":889.98,"close":9.48},{"time":1501632000,"high":9.39,"low":9.39,"open":9.39,"volumefrom":58.18,"volumeto":546.31,"close":9.39},{"time":1501718400,"high":9.69,"low":9.69,"open":9.69,"volumefrom":95.2,"volumeto":922.49,"close":9.69},{"time":1501804800,"high":9.93,"low":9.93,"open":9.93,"volumefrom":100.47,"volumeto":997.67,"close":9.93},{"time":1501891200,"high":11.26,"low":11.26,"open":11.26,"volumefrom":82.47,"volumeto":928.61,"close":11.26},{"time":1501977600,"high":11.15,"low":3.09,"open":11.15,"volumefrom":92.2,"volumeto":953.35,"close":10.34},{"time":1502064000,"high":10.89,"low":3.25,"open":10.89,"volumefrom":142.04,"volumeto":461.63,"close":3.25},{"time":1502150400,"high":6.86,"low":3.28,"open":3.28,"volumefrom":190.14,"volumeto":1291.05,"close":6.79},{"time":1502236800,"high":6.63,"low":6.63,"open":6.63,"volumefrom":146.75,"volumeto":972.95,"close":6.63},{"time":1502323200,"high":10.28,"low":6.78,"open":6.78,"volumefrom":116.91,"volumeto":1101.29,"close":9.42},{"time":1502409600,"high":24.67,"low":5.49,"open":10.05,"volumefrom":98.26,"volumeto":2424.07,"close":24.67},{"time":1502496000,"high":26.14,"low":3.95,"open":26.14,"volumefrom":123.26,"volumeto":1390.37,"close":11.28},{"time":1502582400,"high":16.21,"low":4.12,"open":11.83,"volumefrom":75.03,"volumeto":533.46,"close":7.11},{"time":1502668800,"high":21.19,"low":4.43,"open":7.58,"volumefrom":199.79,"volumeto":3776.03,"close":18.9},{"time":1502755200,"high":18.17,"low":5,"open":18.17,"volumefrom":381.19,"volumeto":2298.58,"close":6.03},{"time":1502841600,"high":14.92,"low":6.35,"open":6.35,"volumefrom":89.79,"volumeto":1339.67,"close":14.92},{"time":1502928000,"high":14.55,"low":10.27,"open":14.55,"volumefrom":43.05,"volumeto":460.63,"close":10.7},{"time":1503014400,"high":14.78,"low":8.94,"open":10.26,"volumefrom":83.86,"volumeto":1174.88,"close":14.01},{"time":1503100800,"high":14.16,"low":12.4,"open":14.16,"volumefrom":292.84,"volumeto":3645.86,"close":12.45},{"time":1503187200,"high":12.2,"low":11.08,"open":12.2,"volumefrom":66.3,"volumeto":808.2,"close":12.19},{"time":1503273600,"high":18.02,"low":12.01,"open":12.01,"volumefrom":87.09,"volumeto":1526.69,"close":17.53},{"time":1503360000,"high":12.27,"low":8.39,"open":12.25,"volumefrom":115.69,"volumeto":1277.22,"close":11.04},{"time":1503446400,"high":11.86,"low":8.95,"open":11.18,"volumefrom":21.6,"volumeto":241.49,"close":11.18},{"time":1503532800,"high":12.48,"low":7.34,"open":11.66,"volumefrom":117.42,"volumeto":928.79,"close":7.91},{"time":1503619200,"high":12.93,"low":8,"open":8,"volumefrom":88.22,"volumeto":1140.68,"close":12.93},{"time":1503705600,"high":12.89,"low":10.88,"open":12.89,"volumefrom":26.03,"volumeto":283.21,"close":10.88},{"time":1503792000,"high":11.44,"low":10.86,"open":10.86,"volumefrom":0.1659,"volumeto":1.9,"close":11.44},{"time":1503878400,"high":11.56,"low":10.89,"open":11.56,"volumefrom":98.19,"volumeto":1069.29,"close":10.89},{"time":1503964800,"high":13.79,"low":11.4,"open":11.4,"volumefrom":1.31,"volumeto":18.06,"close":13.79},{"time":1504051200,"high":13.75,"low":13.75,"open":13.75,"volumefrom":1.07,"volumeto":14.71,"close":13.75},{"time":1504137600,"high":1894.04,"low":14.21,"open":14.21,"volumefrom":336.79,"volumeto":41431.91,"close":123.02},{"time":1504224000,"high":128.46,"low":10.83,"open":127.87,"volumefrom":659.63,"volumeto":18040.88,"close":27.35},{"time":1504310400,"high":27.08,"low":20.58,"open":25.43,"volumefrom":32.44,"volumeto":713.68,"close":22},{"time":1504396800,"high":30.1,"low":11.84,"open":22.18,"volumefrom":210.46,"volumeto":2536.04,"close":12.05},{"time":1504483200,"high":22.71,"low":11.15,"open":11.15,"volumefrom":54.68,"volumeto":933.39,"close":17.07},{"time":1504569600,"high":22.49,"low":12.14,"open":17.63,"volumefrom":8.57,"volumeto":156.49,"close":18.26},{"time":1504656000,"high":25.4,"low":12.48,"open":19.03,"volumefrom":56.14,"volumeto":1038.59,"close":18.5},{"time":1504742400,"high":18.57,"low":10.22,"open":18.57,"volumefrom":147.47,"volumeto":2523.21,"close":17.11},{"time":1504828800,"high":17.28,"low":9.55,"open":16.6,"volumefrom":117.81,"volumeto":1634.02,"close":13.87},{"time":1504915200,"high":15.09,"low":9.54,"open":13.89,"volumefrom":26.26,"volumeto":308.03,"close":11.73},{"time":1505001600,"high":15.56,"low":9.36,"open":9.36,"volumefrom":266.09,"volumeto":3376.68,"close":12.69},{"time":1505088000,"high":15.51,"low":12.6,"open":12.6,"volumefrom":21.17,"volumeto":328.35,"close":15.51},{"time":1505174400,"high":15.29,"low":12.9,"open":15.29,"volumefrom":416.41,"volumeto":5921.35,"close":14.22},{"time":1505260800,"high":14.98,"low":9.29,"open":14.65,"volumefrom":187.98,"volumeto":2103.5,"close":11.19},{"time":1505347200,"high":17.68,"low":7.83,"open":9.37,"volumefrom":90.59,"volumeto":912.24,"close":10.07},{"time":1505433600,"high":18.42,"low":9.86,"open":10.11,"volumefrom":79.37,"volumeto":1462,"close":18.42},{"time":1505520000,"high":18.34,"low":11.46,"open":18.34,"volumefrom":130.02,"volumeto":1798.18,"close":13.83},{"time":1505606400,"high":14.35,"low":11.43,"open":13.8,"volumefrom":78.67,"volumeto":1128.91,"close":14.35},{"time":1505692800,"high":18.28,"low":9.96,"open":15.95,"volumefrom":65.19,"volumeto":1059.99,"close":16.26},{"time":1505779200,"high":17.51,"low":14.47,"open":15.5,"volumefrom":8.54,"volumeto":149.54,"close":17.51},{"time":1505865600,"high":19.37,"low":9.45,"open":17.39,"volumefrom":87.74,"volumeto":829.14,"close":9.45},{"time":1505952000,"high":13.34,"low":8.92,"open":9.42,"volumefrom":84.67,"volumeto":918.67,"close":10.85},{"time":1506038400,"high":10.8,"low":9.91,"open":10.8,"volumefrom":0.1778,"volumeto":1.76,"close":9.91},{"time":1506124800,"high":12.42,"low":9.16,"open":10.42,"volumefrom":85.13,"volumeto":1057.31,"close":12.42},{"time":1506211200,"high":12.03,"low":8.08,"open":12.03,"volumefrom":22.39,"volumeto":180.91,"close":8.08},{"time":1506297600,"high":12.97,"low":8.66,"open":8.66,"volumefrom":62.52,"volumeto":810.88,"close":12.97},{"time":1506384000,"high":12.84,"low":8.56,"open":12.84,"volumefrom":85.25,"volumeto":1030.67,"close":12.09},{"time":1506470400,"high":14.16,"low":12.64,"open":13.09,"volumefrom":64.41,"volumeto":912.05,"close":14.16},{"time":1506556800,"high":14.11,"low":9.59,"open":14.11,"volumefrom":77.36,"volumeto":1052.1,"close":13.6},{"time":1506643200,"high":13.53,"low":9.83,"open":13.52,"volumefrom":72.01,"volumeto":928.21,"close":12.89},{"time":1506729600,"high":13.56,"low":12.6,"open":13.47,"volumefrom":91.38,"volumeto":1155.96,"close":12.65},{"time":1506816000,"high":12.77,"low":10.35,"open":12.77,"volumefrom":100.96,"volumeto":1110.56,"close":11},{"time":1506902400,"high":12.15,"low":11,"open":11,"volumefrom":4.57,"volumeto":50.27,"close":11},{"time":1506988800,"high":13.81,"low":10.79,"open":10.79,"volumefrom":86.02,"volumeto":928.16,"close":10.79},{"time":1507075200,"high":13.68,"low":10.55,"open":10.55,"volumefrom":115.86,"volumeto":1584.96,"close":13.68},{"time":1507161600,"high":14.12,"low":10.8,"open":14.01,"volumefrom":69.07,"volumeto":968.36,"close":14.02},{"time":1507248000,"high":14.18,"low":14.18,"open":14.18,"volumefrom":0,"volumeto":0,"close":14.18},{"time":1507334400,"high":15.08,"low":12.09,"open":14.39,"volumefrom":22.33,"volumeto":275.78,"close":12.35},{"time":1507420800,"high":15.46,"low":8.53,"open":12.84,"volumefrom":70.6,"volumeto":967.22,"close":13.7},{"time":1507507200,"high":14.19,"low":14.19,"open":14.19,"volumefrom":0,"volumeto":0,"close":14.19},{"time":1507593600,"high":13.63,"low":11.94,"open":11.94,"volumefrom":0.1312,"volumeto":1.79,"close":13.63},{"time":1507680000,"high":15.64,"low":10.95,"open":13.8,"volumefrom":65.18,"volumeto":1013.55,"close":15.55},{"time":1507766400,"high":17.6,"low":10.9,"open":17.51,"volumefrom":129.81,"volumeto":2174.32,"close":16.75},{"time":1507852800,"high":17.38,"low":12.4,"open":17.38,"volumefrom":0.6891,"volumeto":8.54,"close":12.4},{"time":1507939200,"high":18.83,"low":7.71,"open":12.81,"volumefrom":100.31,"volumeto":773.39,"close":7.71},{"time":1508025600,"high":18.33,"low":7.53,"open":7.53,"volumefrom":18.62,"volumeto":295.31,"close":15.86},{"time":1508112000,"high":18.56,"low":12.56,"open":12.56,"volumefrom":65.8,"volumeto":1056.75,"close":16.06},{"time":1508198400,"high":18.04,"low":9.85,"open":18.04,"volumefrom":105.59,"volumeto":1314.6,"close":12.45},{"time":1508284800,"high":17.97,"low":11.16,"open":15.05,"volumefrom":63.23,"volumeto":705.65,"close":11.16},{"time":1508371200,"high":17.91,"low":11.4,"open":11.4,"volumefrom":110.8,"volumeto":1982.21,"close":17.89},{"time":1508457600,"high":18.82,"low":13.3,"open":18.82,"volumefrom":43.08,"volumeto":810.77,"close":18.82},{"time":1508544000,"high":18.85,"low":16.75,"open":16.75,"volumefrom":67.82,"volumeto":1278.41,"close":18.85},{"time":1508630400,"high":18.78,"low":15.34,"open":18.78,"volumefrom":70.78,"volumeto":1329.25,"close":18.78},{"time":1508716800,"high":18.53,"low":16.65,"open":18.53,"volumefrom":6.64,"volumeto":110.56,"close":16.65},{"time":1508803200,"high":17.31,"low":9.37,"open":15.55,"volumefrom":2427.42,"volumeto":28619.28,"close":11.79},{"time":1508889600,"high":15.77,"low":12.74,"open":12.75,"volumefrom":7.72,"volumeto":121.74,"close":15.77},{"time":1508976000,"high":17.06,"low":9.43,"open":16.19,"volumefrom":149.33,"volumeto":1408.18,"close":9.43},{"time":1509062400,"high":15.54,"low":8.65,"open":9.23,"volumefrom":155.3,"volumeto":2326.39,"close":14.98},{"time":1509148800,"high":15.27,"low":8.62,"open":14.88,"volumefrom":165,"volumeto":2450.25,"close":14.85},{"time":1509235200,"high":15.94,"low":12.29,"open":15.94,"volumefrom":4.99,"volumeto":61.33,"close":12.29},{"time":1509321600,"high":15.87,"low":12.24,"open":12.24,"volumefrom":162.49,"volumeto":2578.72,"close":15.87},{"time":1509408000,"high":16.72,"low":16.57,"open":16.72,"volumefrom":166.38,"volumeto":2756.92,"close":16.57},{"time":1509494400,"high":17.3,"low":9.86,"open":17.3,"volumefrom":8.17,"volumeto":80.56,"close":9.86},{"time":1509580800,"high":15.45,"low":9.83,"open":15.45,"volumefrom":198.75,"volumeto":3070.69,"close":15.45},{"time":1509667200,"high":15.95,"low":15.73,"open":15.73,"volumefrom":184.14,"volumeto":2896.52,"close":15.73},{"time":1509753600,"high":16.2,"low":10.54,"open":16.2,"volumefrom":192.52,"volumeto":2976.36,"close":15.46},{"time":1509840000,"high":16.33,"low":10.35,"open":15.52,"volumefrom":18.25,"volumeto":189.07,"close":10.36},{"time":1509926400,"high":15.62,"low":15.45,"open":15.45,"volumefrom":184.16,"volumeto":2876.58,"close":15.62},{"time":1510012800,"high":15.94,"low":14.92,"open":15.94,"volumefrom":196.94,"volumeto":3121.5,"close":15.85},{"time":1510099200,"high":16.61,"low":14.87,"open":16.61,"volumefrom":210.22,"volumeto":3136.48,"close":14.92},{"time":1510185600,"high":14.33,"low":14.19,"open":14.29,"volumefrom":202.63,"volumeto":2877.35,"close":14.2},{"time":1510272000,"high":14.9,"low":7.22,"open":13.07,"volumefrom":218.17,"volumeto":2851.48,"close":13.07},{"time":1510358400,"high":12.67,"low":9.4,"open":9.54,"volumefrom":13.79,"volumeto":146.86,"close":10.65},{"time":1510444800,"high":13.34,"low":8.81,"open":8.81,"volumefrom":3.73,"volumeto":48.08,"close":12.89},{"time":1510531200,"high":14.31,"low":8.71,"open":14.3,"volumefrom":210.74,"volumeto":2756.48,"close":13.08},{"time":1510617600,"high":13.21,"low":13.19,"open":13.19,"volumefrom":3.08,"volumeto":40.69,"close":13.21},{"time":1510704000,"high":14.58,"low":13.84,"open":14.58,"volumefrom":109.57,"volumeto":1516.45,"close":13.84},{"time":1510790400,"high":13.35,"low":13.34,"open":13.35,"volumefrom":215.22,"volumeto":2871.03,"close":13.34},{"time":1510876800,"high":16.29,"low":13.09,"open":13.1,"volumefrom":221.04,"volumeto":2893.41,"close":13.09},{"time":1510963200,"high":13.23,"low":10.89,"open":13.23,"volumefrom":71.69,"volumeto":948.46,"close":13.23},{"time":1511049600,"high":13.67,"low":11.26,"open":13.67,"volumefrom":4,"volumeto":45.2,"close":11.3},{"time":1511136000,"high":14.02,"low":11.35,"open":11.35,"volumefrom":144.54,"volumeto":2026.45,"close":14.02},{"time":1511222400,"high":13.76,"low":11.34,"open":13.19,"volumefrom":115.42,"volumeto":1585.87,"close":13.74},{"time":1511308800,"high":14,"low":11.53,"open":13.97,"volumefrom":139.24,"volumeto":1704.3,"close":12.24},{"time":1511395200,"high":13.61,"low":11.22,"open":11.91,"volumefrom":72.48,"volumeto":819.02,"close":11.3},{"time":1511481600,"high":13.92,"low":11.37,"open":11.56,"volumefrom":0.6278,"volumeto":8.74,"close":13.92},{"time":1511568000,"high":14.86,"low":12.27,"open":14.86,"volumefrom":64.79,"volumeto":947.23,"close":14.62},{"time":1511654400,"high":15.56,"low":15.38,"open":15.56,"volumefrom":0.1804,"volumeto":2.77,"close":15.38},{"time":1511740800,"high":16.06,"low":16.06,"open":16.06,"volumefrom":63.49,"volumeto":1019.65,"close":16.06},{"time":1511827200,"high":16.84,"low":13.87,"open":16.66,"volumefrom":65.63,"volumeto":910.29,"close":13.87},{"time":1511913600,"high":15.74,"low":13.7,"open":13.77,"volumefrom":68.32,"volumeto":1075.36,"close":15.74},{"time":1512000000,"high":15.91,"low":15.91,"open":15.91,"volumefrom":67.71,"volumeto":1077.27,"close":15.91},{"time":1512086400,"high":18.27,"low":17.33,"open":17.38,"volumefrom":101.97,"volumeto":1772.24,"close":17.38},{"time":1512172800,"high":18.55,"low":15.28,"open":17.46,"volumefrom":12.3,"volumeto":226.44,"close":18.41},{"time":1512259200,"high":20.85,"low":17.94,"open":18.97,"volumefrom":70.54,"volumeto":1265.49,"close":17.94},{"time":1512345600,"high":18.6,"low":17.23,"open":18.54,"volumefrom":68.21,"volumeto":1175.26,"close":17.23},{"time":1512432000,"high":17.22,"low":11.67,"open":17.22,"volumefrom":8.99,"volumeto":104.91,"close":11.67},{"time":1512518400,"high":22,"low":13.75,"open":13.75,"volumefrom":67.43,"volumeto":1483.46,"close":22},{"time":1512604800,"high":26.96,"low":16.85,"open":26.96,"volumefrom":97.22,"volumeto":1685.79,"close":17.34},{"time":1512691200,"high":25.68,"low":16.05,"open":16.51,"volumefrom":85.06,"volumeto":1367.76,"close":16.08},{"time":1512777600,"high":23.75,"low":13.99,"open":14.87,"volumefrom":120.8,"volumeto":2827.93,"close":23.41},{"time":1512864000,"high":23.75,"low":12.35,"open":23.75,"volumefrom":9.74,"volumeto":120.29,"close":12.35},{"time":1512950400,"high":13.72,"low":13.72,"open":13.72,"volumefrom":0,"volumeto":0,"close":13.72},{"time":1513036800,"high":25.63,"low":14.01,"open":14.01,"volumefrom":2.82,"volumeto":61.87,"close":21.94},{"time":1513123200,"high":20.91,"low":20.91,"open":20.91,"volumefrom":0,"volumeto":0,"close":20.91},{"time":1513209600,"high":26,"low":8.24,"open":21.14,"volumefrom":11.19,"volumeto":290.94,"close":26},{"time":1513296000,"high":396.64,"low":22.48,"open":27.8,"volumefrom":650.15,"volumeto":88075.82,"close":135.47},{"time":1513382400,"high":443.4,"low":98.7,"open":152.44,"volumefrom":412.24,"volumeto":62738.81,"close":152.19},{"time":1513468800,"high":149.99,"low":97.24,"open":149.99,"volumefrom":99.76,"volumeto":10190.48,"close":102.15},{"time":1513555200,"high":103.99,"low":74.07,"open":101.65,"volumefrom":23.51,"volumeto":1829.31,"close":77.81},{"time":1513641600,"high":92.51,"low":68.47,"open":71.86,"volumefrom":29.8,"volumeto":2315.46,"close":77.7},{"time":1513728000,"high":86.87,"low":62.56,"open":72.99,"volumefrom":10.53,"volumeto":693.4,"close":65.85},{"time":1513814400,"high":62.53,"low":46.91,"open":62.53,"volumefrom":11.3,"volumeto":704.67,"close":62.36},{"time":1513900800,"high":54.51,"low":41.01,"open":54.51,"volumefrom":9.31,"volumeto":382.27,"close":41.06},{"time":1513987200,"high":55.35,"low":43.26,"open":43.26,"volumefrom":2.46,"volumeto":106.49,"close":43.29},{"time":1514073600,"high":52.48,"low":41.47,"open":41.47,"volumefrom":11.36,"volumeto":471.21,"close":41.48},{"time":1514160000,"high":52.48,"low":41.61,"open":41.61,"volumefrom":7.61,"volumeto":399.37,"close":52.48},{"time":1514246400,"high":59.78,"low":34.84,"open":59.78,"volumefrom":7.81,"volumeto":463.91,"close":59.4},{"time":1514332800,"high":58.12,"low":34.53,"open":58.12,"volumefrom":22.12,"volumeto":1240.93,"close":56.1},{"time":1514419200,"high":52.4,"low":36,"open":52.4,"volumefrom":11.18,"volumeto":579.01,"close":51.79},{"time":1514505600,"high":51.77,"low":37.2,"open":51.77,"volumefrom":14.5,"volumeto":656.13,"close":45.25},{"time":1514592000,"high":39.4,"low":31.33,"open":39.4,"volumefrom":17.87,"volumeto":703.9,"close":39.39},{"time":1514678400,"high":43.53,"low":43.53,"open":43.53,"volumefrom":0,"volumeto":0,"close":43.53},{"time":1514764800,"high":42.26,"low":40.9,"open":42.26,"volumefrom":0.67,"volumeto":27.4,"close":40.9},{"time":1514851200,"high":46.36,"low":37.48,"open":44.88,"volumefrom":11.84,"volumeto":448.97,"close":37.92},{"time":1514937600,"high":53.05,"low":38.95,"open":38.95,"volumefrom":2.82,"volumeto":110.71,"close":39.26},{"time":1515024000,"high":49.94,"low":39.01,"open":39.32,"volumefrom":40.73,"volumeto":1916.75,"close":47.06},{"time":1515110400,"high":56.76,"low":19.04,"open":52.56,"volumefrom":71.27,"volumeto":4027.47,"close":56.51},{"time":1515196800,"high":85.86,"low":57.34,"open":57.34,"volumefrom":63.33,"volumeto":4892.88,"close":77.26},{"time":1515283200,"high":85.67,"low":55.19,"open":73.01,"volumefrom":16.69,"volumeto":1137.59,"close":68.16},{"time":1515369600,"high":748.81,"low":62.9,"open":62.9,"volumefrom":169.78,"volumeto":17792.94,"close":104.8},{"time":1515456000,"high":166.39,"low":72.36,"open":101.25,"volumefrom":59.54,"volumeto":8614.84,"close":144.69},{"time":1515542400,"high":745.97,"low":85.46,"open":149.19,"volumefrom":422.37,"volumeto":54823.63,"close":129.8},{"time":1515628800,"high":399.24,"low":115.78,"open":115.78,"volumefrom":157.9,"volumeto":21875.47,"close":138.54},{"time":1515715200,"high":415.24,"low":144.09,"open":144.09,"volumefrom":165.04,"volumeto":57108.79,"close":346.03},{"time":1515801600,"high":391.69,"low":270.76,"open":356.08,"volumefrom":59.68,"volumeto":19363.77,"close":324.46},{"time":1515888000,"high":310.69,"low":205.94,"open":310.69,"volumefrom":20.8,"volumeto":4312.05,"close":207.31},{"time":1515974400,"high":245.38,"low":145.73,"open":245.38,"volumefrom":23.55,"volumeto":4173.53,"close":177.22},{"time":1516060800,"high":160.32,"low":133.13,"open":146.67,"volumefrom":8.06,"volumeto":1292.18,"close":160.32},{"time":1516147200,"high":158.62,"low":69.81,"open":158.62,"volumefrom":48.52,"volumeto":5849.57,"close":120.56},{"time":1516233600,"high":318.5,"low":85.66,"open":120.7,"volumefrom":177.24,"volumeto":18222.04,"close":102.81},{"time":1516320000,"high":201.63,"low":97.93,"open":104.85,"volumefrom":52.18,"volumeto":7448.7,"close":142.75},{"time":1516406400,"high":181.15,"low":127.83,"open":158.39,"volumefrom":24.9,"volumeto":3889.88,"close":156.22},{"time":1516492800,"high":311.85,"low":119.2,"open":141.14,"volumefrom":248.3,"volumeto":38429.39,"close":154.77},{"time":1516579200,"high":192.5,"low":132.15,"open":144.91,"volumefrom":65.18,"volumeto":10573.5,"close":162.22},{"time":1516665600,"high":162.87,"low":51.9,"open":162.87,"volumefrom":20.78,"volumeto":3262.67,"close":157.01},{"time":1516752000,"high":165.26,"low":140.12,"open":165.26,"volumefrom":25.31,"volumeto":3821.3,"close":150.98},{"time":1516838400,"high":162.61,"low":119.92,"open":119.92,"volumefrom":24.31,"volumeto":3754.68,"close":154.45},{"time":1516924800,"high":150.68,"low":119.26,"open":136.47,"volumefrom":16.97,"volumeto":2125.66,"close":125.26},{"time":1517011200,"high":162.27,"low":124.68,"open":129.27,"volumefrom":47.66,"volumeto":6046.15,"close":126.86},{"time":1517097600,"high":138.51,"low":125.68,"open":130.27,"volumefrom":5.9,"volumeto":778.33,"close":131.92},{"time":1517184000,"high":156.6,"low":119.98,"open":126.04,"volumefrom":4.75,"volumeto":572.04,"close":120.43},{"time":1517270400,"high":113.2,"low":106.13,"open":108.35,"volumefrom":5.83,"volumeto":618.74,"close":106.13},{"time":1517356800,"high":135.51,"low":90.22,"open":107.38,"volumefrom":24.46,"volumeto":2236.87,"close":91.45},{"time":1517443200,"high":126.42,"low":81.02,"open":81.5,"volumefrom":44.08,"volumeto":3663.49,"close":83.11},{"time":1517529600,"high":122.15,"low":78.99,"open":80.88,"volumefrom":29.29,"volumeto":2324.16,"close":79.35},{"time":1517616000,"high":103.34,"low":80,"open":82.75,"volumefrom":14.71,"volumeto":1495.57,"close":101.67},{"time":1517702400,"high":113.98,"low":74.63,"open":90.32,"volumefrom":19.97,"volumeto":1670.69,"close":83.66},{"time":1517788800,"high":96.15,"low":60.85,"open":70.62,"volumefrom":26.28,"volumeto":1695.06,"close":64.5},{"time":1517875200,"high":77.63,"low":66.25,"open":71.61,"volumefrom":30.28,"volumeto":2215.28,"close":73.16},{"time":1517961600,"high":72.19,"low":65.34,"open":72.13,"volumefrom":5.35,"volumeto":349.57,"close":65.34},{"time":1518048000,"high":75.17,"low":57.85,"open":71.08,"volumefrom":58.93,"volumeto":3409.1,"close":57.85},{"time":1518134400,"high":80.01,"low":43.55,"open":43.55,"volumefrom":24.12,"volumeto":1929.84,"close":80.01},{"time":1518220800,"high":81.82,"low":67.7,"open":78.84,"volumefrom":26.84,"volumeto":1835.86,"close":68.4},{"time":1518307200,"high":89.74,"low":57.06,"open":64.53,"volumefrom":42.76,"volumeto":3422.51,"close":80.04},{"time":1518393600,"high":123.69,"low":70.38,"open":88.22,"volumefrom":42.89,"volumeto":5305.06,"close":123.69},{"time":1518480000,"high":118.6,"low":118.6,"open":118.6,"volumefrom":0,"volumeto":0,"close":118.6},{"time":1518566400,"high":131.66,"low":65.49,"open":131.66,"volumefrom":32.72,"volumeto":2638.87,"close":80.65},{"time":1518652800,"high":138.77,"low":69.44,"open":85.31,"volumefrom":79.35,"volumeto":5813.97,"close":73.27},{"time":1518739200,"high":134.8,"low":74.4,"open":74.4,"volumefrom":22.51,"volumeto":1706.71,"close":75.82},{"time":1518825600,"high":152.48,"low":80.87,"open":82.59,"volumefrom":28.5,"volumeto":2576.12,"close":90.39},{"time":1518912000,"high":143.76,"low":84.85,"open":84.85,"volumefrom":3.2,"volumeto":277.02,"close":86.57},{"time":1518998400,"high":93.09,"low":56.15,"open":92.92,"volumefrom":10.34,"volumeto":962.55,"close":93.09},{"time":1519084800,"high":111.37,"low":72.66,"open":93.71,"volumefrom":25.08,"volumeto":2793.16,"close":111.37},{"time":1519171200,"high":103.71,"low":52.41,"open":103.71,"volumefrom":98.36,"volumeto":6605.86,"close":67.16},{"time":1519257600,"high":95.63,"low":63.1,"open":63.1,"volumefrom":18.13,"volumeto":1220.33,"close":67.31},{"time":1519344000,"high":99.72,"low":65.11,"open":69.55,"volumefrom":12.45,"volumeto":949.81,"close":76.29},{"time":1519430400,"high":72.76,"low":62.12,"open":72.76,"volumefrom":17.65,"volumeto":1283.16,"close":72.7},{"time":1519516800,"high":72,"low":62.47,"open":71.98,"volumefrom":3.81,"volumeto":238.01,"close":62.47},{"time":1519603200,"high":77.37,"low":67.12,"open":67.12,"volumefrom":34.61,"volumeto":2677.78,"close":77.37},{"time":1519689600,"high":79.38,"low":64.82,"open":79.38,"volumefrom":21.48,"volumeto":1392.33,"close":64.82},{"time":1519776000,"high":76.99,"low":50.35,"open":63.23,"volumefrom":37.22,"volumeto":1874.03,"close":50.35},{"time":1519862400,"high":51.97,"low":51.68,"open":51.68,"volumefrom":0.3801,"volumeto":19.64,"close":51.97}],"TimeTo":1519862400,"TimeFrom":1497052800000,"FirstValueInArray":true,"ConversionType":{"type":"multiply","conversionSymbol":"BTC"}}